xalpha/__init__.py
xalpha/backtest.py
xalpha/caldate.csv
xalpha/cons.py
xalpha/evaluate.py
xalpha/exceptions.py
xalpha/holiday.json
xalpha/indicator.py
xalpha/info.py
xalpha/investinghooks.py
xalpha/misc.py
xalpha/multiple.py
xalpha/policy.py
xalpha/provider.py
xalpha/realtime.py
xalpha/record.py
xalpha/remain.py
xalpha/toolbox.py
xalpha/trade.py
xalpha/universal.py
xalpha-0.12.3.dist-info/licenses/LICENSE
xalpha-0.12.3.dist-info/METADATA
xalpha-0.12.3.dist-info/WHEEL
xalpha-0.12.3.dist-info/top_level.txt
xalpha-0.12.3.dist-info/RECORD
