Metadata-Version: 2.4
Name: xalpha
Version: 0.12.3
Summary: all about fund investment
Home-page: https://github.com/refraction-ray/xalpha
Author: refraction-ray
Author-email: znfesnpbh@gmail.com
Classifier: Programming Language :: Python :: 3
Classifier: License :: OSI Approved :: MIT License
Classifier: Operating System :: OS Independent
License-File: LICENSE
Requires-Dist: lxml
Requires-Dist: pandas<2.0
Requires-Dist: xlrd>=1.0.0
Requires-Dist: numpy<2.0
Requires-Dist: scipy
Requires-Dist: matplotlib
Requires-Dist: requests
Requires-Dist: pyecharts==1.7.1; python_version <= "3.9"
Requires-Dist: pyecharts==1.9.1; python_version > "3.9"
Requires-Dist: beautifulsoup4>=4.9.0
Requires-Dist: sqlalchemy<2.0
Requires-Dist: pysocks
Dynamic: author
Dynamic: author-email
Dynamic: classifier
Dynamic: description
Dynamic: description-content-type
Dynamic: home-page
Dynamic: license-file
Dynamic: requires-dist
Dynamic: summary
